gff2bed/__init__.py
gff2bed/gff2bed.py
gff2bed/version.py
gff2bed-1.0.3.dist-info/LICENSE
gff2bed-1.0.3.dist-info/METADATA
gff2bed-1.0.3.dist-info/WHEEL
gff2bed-1.0.3.dist-info/top_level.txt
gff2bed-1.0.3.dist-info/RECORD
