Metadata-Version: 2.1
Name: gff2bed
Version: 1.0.3
Summary: Convert GFF3-formatted data to BED format
Author-email: Anthony Aylward <aaylward@salk.edu>
Project-URL: Homepage, https://gitlab.com/salk-tm/gff2bed
Project-URL: Documentation, https://salk-tm.gitlab.io/gff2bed
Classifier: Programming Language :: Python :: 3
Classifier: License :: OSI Approved :: MIT License
Classifier: Operating System :: OS Independent
Requires-Python: >=3.7
License-File: LICENSE
